magicprof.pth
magicprof.py
magicprof-0.0.1.dist-info/METADATA
magicprof-0.0.1.dist-info/WHEEL
magicprof-0.0.1.dist-info/licenses/LICENSE
magicprof-0.0.1.dist-info/RECORD
