Metadata-Version: 2.4
Name: magicprof
Version: 0.0.1
Summary: Automatically instrumented python profiling
Author-email: Austin Raney <aaraney@protonmail.com>
License-Expression: MIT
License-File: LICENSE
Requires-Python: >=3.8
